gauth_python_package/__init__.py
gauth_python_package/gauth_python.py
gauth_python_package-0.1.2.dist-info/LICENSE
gauth_python_package-0.1.2.dist-info/METADATA
gauth_python_package-0.1.2.dist-info/WHEEL
gauth_python_package-0.1.2.dist-info/top_level.txt
gauth_python_package-0.1.2.dist-info/RECORD
