Metadata-Version: 2.1
Name: gauth-python-package
Version: 0.1.2
Summary: Python sdk from Gauth.
Home-page: UNKNOWN
Author: Noh Gaseong
License: MIT
Platform: UNKNOWN
License-File: LICENSE
